assertionlib/README.rst
assertionlib/__init__.py
assertionlib/__version__.py
assertionlib/assertion_functions.py
assertionlib/dataclass.py
assertionlib/functions.py
assertionlib/manager.py
assertionlib/manager.pyi
assertionlib/ndrepr.py
assertionlib/protocol.pyi
assertionlib/py.typed
AssertionLib-3.2.2.dist-info/LICENSE.md
AssertionLib-3.2.2.dist-info/METADATA
AssertionLib-3.2.2.dist-info/WHEEL
AssertionLib-3.2.2.dist-info/top_level.txt
AssertionLib-3.2.2.dist-info/RECORD
